throttlebuster/__init__.py
throttlebuster/__main__.py
throttlebuster/cli.py
throttlebuster/constants.py
throttlebuster/core.py
throttlebuster/exceptions.py
throttlebuster/helpers.py
throttlebuster/models.py
throttlebuster/py.typed
throttlebuster-0.1.10.dist-info/METADATA
throttlebuster-0.1.10.dist-info/WHEEL
throttlebuster-0.1.10.dist-info/entry_points.txt
throttlebuster-0.1.10.dist-info/licenses/LICENSE
throttlebuster-0.1.10.dist-info/RECORD
