Metadata-Version: 2.4
Name: throttlebuster
Version: 0.1.10
Summary: Accelerate file downloads by overcoming common throttling restrictions.
Project-URL: homepage, https://github.com/Simatwa/throttlebuster
Project-URL: repository, https://github.com/Simatwa/throttlebuster
Project-URL: documentation, https://github.com/Simatwa/throttlebuster
Author-email: smartwa <smartwacaleb@gmail.com>
License-Expression: Apache-2.0
License-File: LICENSE
Classifier: Intended Audience :: Developers
Classifier: License :: OSI Approved :: Apache Software License
Classifier: Operating System :: OS Independent
Classifier: Programming Language :: Python :: 3
Classifier: Programming Language :: Python :: 3.10
Classifier: Programming Language :: Python :: 3.11
Classifier: Programming Language :: Python :: 3.12
Classifier: Programming Language :: Python :: 3.13
Classifier: Topic :: Communications :: File Sharing
Classifier: Topic :: Utilities
Requires-Python: >=3.10
Requires-Dist: aiofiles>=24.1.0
Requires-Dist: httpx>=0.28.1
Requires-Dist: tqdm>=4.67.1
Provides-Extra: cli
Requires-Dist: click>=8.2.1; extra == 'cli'
Requires-Dist: rich>=14.1.0; extra == 'cli'
